megaradrp/__init__.py
megaradrp/_version.py
megaradrp/datamodel.py
megaradrp/datatype.py
megaradrp/drp.yaml
megaradrp/loader.py
megaradrp/ntypes.py
megaradrp/requirements.py
megaradrp/taggers.py
megaradrp/utils.py
megaradrp/validators.py
megaradrp/visualization.py
megaradrp/core/__init__.py
megaradrp/core/correctors.py
megaradrp/core/recipe.py
megaradrp/core/utils.py
megaradrp/db/__init__.py
megaradrp/db/control.py
megaradrp/db/model.py
megaradrp/instrument/__init__.py
megaradrp/instrument/focalplane.py
megaradrp/instrument/ienums.py
megaradrp/instrument/components/__init__.py
megaradrp/instrument/components/calibrationunit.py
megaradrp/instrument/components/cover.py
megaradrp/instrument/components/detector.py
megaradrp/instrument/components/fibermos.py
megaradrp/instrument/components/instrument.py
megaradrp/instrument/components/lamps.py
megaradrp/instrument/components/psslit.py
megaradrp/instrument/components/shutter.py
megaradrp/instrument/components/telescope.py
megaradrp/instrument/components/wheel.py
megaradrp/instrument/configs/__init__.py
megaradrp/instrument/configs/component-06fc5d6d-d20b-4eba-b3fa-57696f0a1103.json
megaradrp/instrument/configs/component-2e02e135-2325-47c9-9975-466b445b0b8b.json
megaradrp/instrument/configs/component-3d24fe52-f28d-4162-9124-f447daded7d5.json
megaradrp/instrument/configs/component-715c7ced-f989-42a6-bb74-a5b5cda0495c.json
megaradrp/instrument/configs/component-78f6d437-85d6-4d7a-bdb7-1e043368b442.json
megaradrp/instrument/configs/component-97d48545-3258-473e-9311-00e390999d52.json
megaradrp/instrument/configs/instrument-4fd05b24-2ed9-457b-b563-a3c618bb1d4c.json
megaradrp/instrument/configs/instrument-66f2283e-3049-4d4b-8ef1-14d62fcb611d.json
megaradrp/instrument/configs/instrument-9a86b2b2-3f7d-48ec-8f4f-3780ec967c90.json
megaradrp/instrument/configs/instrument-9f3fecbf-376c-47ae-a188-313b7d829104.json
megaradrp/instrument/configs/instrument-ca3558e3-e50d-4bbc-86bd-da50a0998a48.json
megaradrp-0.19.dist-info/licenses/AUTHORS.rst
megaradrp-0.19.dist-info/licenses/LICENSE.txt
megaradrp-0.19.dist-info/METADATA
megaradrp-0.19.dist-info/WHEEL
megaradrp-0.19.dist-info/entry_points.txt
megaradrp-0.19.dist-info/top_level.txt
megaradrp-0.19.dist-info/RECORD
