Metadata-Version: 2.4
Name: megaradrp
Version: 0.19
Summary: MEGARA Data Reduction Pipeline
Author-email: Sergio Pascual <sergiopr@fis.ucm.es>
License: GPL-3.0-or-later
Project-URL: Homepage, https://github.com/guaix-ucm/megaradrp
Project-URL: Repository, https://github.com/guaix-ucm/megaradrp.git
Project-URL: Documentation, https://megaradrp.readthedocs.io/en/stable/
Classifier: Programming Language :: Python :: 3.10
Classifier: Programming Language :: Python :: 3.11
Classifier: Programming Language :: Python :: 3.12
Classifier: Programming Language :: Python :: 3.13
Classifier: Programming Language :: Python :: 3.14
Classifier: Development Status :: 3 - Alpha
Classifier: Environment :: Console
Classifier: Intended Audience :: Science/Research
Classifier: License :: OSI Approved :: GNU General Public License (GPL)
Classifier: Operating System :: OS Independent
Classifier: Topic :: Scientific/Engineering :: Astronomy
Requires-Python: >=3.10
License-File: LICENSE.txt
License-File: AUTHORS.rst
Requires-Dist: astropy>=6.1.7
Requires-Dist: attrs
Requires-Dist: jsonschema
Requires-Dist: matplotlib
Requires-Dist: numpy
Requires-Dist: numina>=0.36
Requires-Dist: packaging
Requires-Dist: scikit-image
Requires-Dist: scipy>=1.12
Requires-Dist: requests
Provides-Extra: test
Requires-Dist: pytest>=6; extra == "test"
Requires-Dist: pytest-remotedata; extra == "test"
Provides-Extra: docs
Requires-Dist: sphinx; extra == "docs"
Requires-Dist: numpydoc; extra == "docs"
Requires-Dist: sphinx_rtd_theme; extra == "docs"
Provides-Extra: db
Requires-Dist: sqlalchemy; extra == "db"
Requires-Dist: numinadb; extra == "db"
Dynamic: license-file
